nonebot_plugin_dorodoro/__init__.py
nonebot_plugin_dorodoro/config.py
nonebot_plugin_dorodoro/game_logic.py
nonebot_plugin_dorodoro/image_handler.py
nonebot_plugin_dorodoro/images/1bb22576b2e253fae6b2ddca27cd3384.jpg
nonebot_plugin_dorodoro/images/748ad50bef1249c2c16385c4b4c22ed5.jpg
nonebot_plugin_dorodoro/images/abd814eba4fa165f44f3e16fb93b3a72.png
nonebot_plugin_dorodoro/images/ba904a2d0a5779a13b4ab8cd145f5cb2.png
nonebot_plugin_dorodoro/images/bad_ending.jpeg
nonebot_plugin_dorodoro/images/bad_ending.png
nonebot_plugin_dorodoro/images/butterfly_ending.png
nonebot_plugin_dorodoro/images/clouds_ending.jpg
nonebot_plugin_dorodoro/images/dajiao.jpg
nonebot_plugin_dorodoro/images/despot_end_true.jpg
nonebot_plugin_dorodoro/images/doro_ending.png
nonebot_plugin_dorodoro/images/dream_ending.png
nonebot_plugin_dorodoro/images/gaokao_ending.jpeg
nonebot_plugin_dorodoro/images/gingganggoolie_ending.png
nonebot_plugin_dorodoro/images/good_ending.png
nonebot_plugin_dorodoro/images/immortal_end_true.jpg
nonebot_plugin_dorodoro/images/indolent_ending.png
nonebot_plugin_dorodoro/images/jiangwei_ending.jpeg
nonebot_plugin_dorodoro/images/jingshenhunluan_ending.jpeg
nonebot_plugin_dorodoro/images/kaoyan_ending.jpg
nonebot_plugin_dorodoro/images/laborer_ending.png
nonebot_plugin_dorodoro/images/laze_ending.png
nonebot_plugin_dorodoro/images/marry_ending.png
nonebot_plugin_dorodoro/images/moyu_ending.jpg
nonebot_plugin_dorodoro/images/neijuan_ending.jpg
nonebot_plugin_dorodoro/images/netcafe_clerk_end_true.jpg
nonebot_plugin_dorodoro/images/orange_ending.png
nonebot_plugin_dorodoro/images/postgraduate_ending.png
nonebot_plugin_dorodoro/images/procrastination_ending.png
nonebot_plugin_dorodoro/images/race_ending.png
nonebot_plugin_dorodoro/images/shadow_ending.png
nonebot_plugin_dorodoro/images/shekong_ending.jpeg
nonebot_plugin_dorodoro/images/sloth_ending.jpg
nonebot_plugin_dorodoro/images/staffawakening2_ending.png
nonebot_plugin_dorodoro/images/staffawakening_ending.png
nonebot_plugin_dorodoro-1.5.6.dist-info/LICENSE
nonebot_plugin_dorodoro-1.5.6.dist-info/METADATA
nonebot_plugin_dorodoro-1.5.6.dist-info/WHEEL
nonebot_plugin_dorodoro-1.5.6.dist-info/RECORD
