Metadata-Version: 2.3
Name: nonebot_plugin_dorodoro
Version: 1.5.6
Summary: 一个基于文字冒险的游戏插件
License: AGPL3.0
Keywords: nonebot,nonebot2,nonebot_plugin,doro
Author: ATTomatoo
Requires-Python: >=3.8,<4.0
Classifier: License :: Other/Proprietary License
Classifier: Programming Language :: Python :: 3
Classifier: Programming Language :: Python :: 3.8
Classifier: Programming Language :: Python :: 3.9
Classifier: Programming Language :: Python :: 3.10
Classifier: Programming Language :: Python :: 3.11
Classifier: Programming Language :: Python :: 3.12
Classifier: Programming Language :: Python :: 3.13
Requires-Dist: aiofiles (>23.2.0)
Requires-Dist: nonebot-plugin-alconna (>0.57.0)
Requires-Dist: nonebot-plugin-uninfo (>0.7.0)
Requires-Dist: nonebot2 (>2.3.3)
Project-URL: Homepage, https://github.com/ATTomatoo/dorodoro
Project-URL: Repository, https://github.com/ATTomatoo/dorodoro
